[
  {
    "Id": 0,
    "Rank": 19,
    "TimeRank": 0,
    "DmRank": 0,
    "UseNum": 34987,
    "DayUseNum": null,
    "TimeId": 202406,
    "TimeName": "2024年06月",
    "Appid": 2528,
    "AppName": "今日头条",
    "AppLogo": "//core.itracker.cn/mbapp/logo/2528.png",
    "MachineODayNum": null,
    "MachineODayTime": null,
    "MachineOTimeTime": null,
    "Fclassid": 0,
    "Kclassid": 0,
    "FclassName": "综合资讯",
    "KclassName": "新闻资讯",
    "TimeType": 0,
    "Growth": 1.41,
    "DmGrowth": null,
    "Company": null,
    "UseTime": null,
    "TimeGrowth": null,
    "DayMachineNum": null,
    "IsService": false,
    "AppType": 0,
    "Domain": null,
    "IsChanged": 0,
    "CRank": 0,
    "IsMark": false
  },
  {
    "Id": 0,
    "Rank": 22,
    "TimeRank": 0,
    "DmRank": 0,
    "UseNum": 29860,
    "DayUseNum": null,
    "TimeId": 202406,
    "TimeName": "2024年06月",
    "Appid": 3863,
    "AppName": "腾讯新闻",
    "AppLogo": "//core.itracker.cn/mbapp/logo/3863.png",
    "MachineODayNum": null,
    "MachineODayTime": null,
    "MachineOTimeTime": null,
    "Fclassid": 0,
    "Kclassid": 0,
    "FclassName": "综合资讯",
    "KclassName": "新闻资讯",
    "TimeType": 0,
    "Growth": -0.54,
    "DmGrowth": null,
    "Company": null,
    "UseTime": null,
    "TimeGrowth": null,
    "DayMachineNum": null,
    "IsService": false,
    "AppType": 0,
    "Domain": null,
    "IsChanged": 0,
    "CRank": 0,
    "IsMark": false
  },
  {
    "Id": 0,
    "Rank": 39,
    "TimeRank": 0,
    "DmRank": 0,
    "UseNum": 16503,
    "DayUseNum": null,
    "TimeId": 202406,
    "TimeName": "2024年06月",
    "Appid": 4349,
    "AppName": "新浪新闻",
    "AppLogo": "//core.itracker.cn/mbapp/logo/4349.png",
    "MachineODayNum": null,
    "MachineODayTime": null,
    "MachineOTimeTime": null,
    "Fclassid": 0,
    "Kclassid": 0,
    "FclassName": "综合资讯",
    "KclassName": "新闻资讯",
    "TimeType": 0,
    "Growth": -0.83,
    "DmGrowth": null,
    "Company": null,
    "UseTime": null,
    "TimeGrowth": null,
    "DayMachineNum": null,
    "IsService": false,
    "AppType": 0,
    "Domain": null,
    "IsChanged": 0,
    "CRank": 0,
    "IsMark": false
  },
  {
    "Id": 0,
    "Rank": 76,
    "TimeRank": 0,
    "DmRank": 0,
    "UseNum": 8744,
    "DayUseNum": null,
    "TimeId": 202406,
    "TimeName": "2024年06月",
    "Appid": 4066,
    "AppName": "网易新闻",
    "AppLogo": "//core.itracker.cn/mbapp/logo/4066.png",
    "MachineODayNum": null,
    "MachineODayTime": null,
    "MachineOTimeTime": null,
    "Fclassid": 0,
    "Kclassid": 0,
    "FclassName": "综合资讯",
    "KclassName": "新闻资讯",
    "TimeType": 0,
    "Growth": -1.87,
    "DmGrowth": null,
    "Company": null,
    "UseTime": null,
    "TimeGrowth": null,
    "DayMachineNum": null,
    "IsService": false,
    "AppType": 0,
    "Domain": null,
    "IsChanged": 0,
    "CRank": 0,
    "IsMark": false
  },
  {
    "Id": 0,
    "Rank": 96,
    "TimeRank": 0,
    "DmRank": 0,
    "UseNum": 5903,
    "DayUseNum": null,
    "TimeId": 202406,
    "TimeName": "2024年06月",
    "Appid": 3757,
    "AppName": "搜狐新闻",
    "AppLogo": "//core.itracker.cn/mbapp/logo/3757.png",
    "MachineODayNum": null,
    "MachineODayTime": null,
    "MachineOTimeTime": null,
    "Fclassid": 0,
    "Kclassid": 0,
    "FclassName": "综合资讯",
    "KclassName": "新闻资讯",
    "TimeType": 0,
    "Growth": -2.44,
    "DmGrowth": null,
    "Company": null,
    "UseTime": null,
    "TimeGrowth": null,
    "DayMachineNum": null,
    "IsService": false,
    "AppType": 0,
    "Domain": null,
    "IsChanged": 0,
    "CRank": 0,
    "IsMark": false
  },
  {
    "Id": 0,
    "Rank": 142,
    "TimeRank": 0,
    "DmRank": 0,
    "UseNum": 3001,
    "DayUseNum": null,
    "TimeId": 202406,
    "TimeName": "2024年06月",
    "Appid": 6760,
    "AppName": "一点资讯",
    "AppLogo": "//core.itracker.cn/mbapp/logo/6760.png",
    "MachineODayNum": null,
    "MachineODayTime": null,
    "MachineOTimeTime": null,
    "Fclassid": 0,
    "Kclassid": 0,
    "FclassName": "综合资讯",
    "KclassName": "新闻资讯",
    "TimeType": 0,
    "Growth": -2.81,
    "DmGrowth": null,
    "Company": null,
    "UseTime": null,
    "TimeGrowth": null,
    "DayMachineNum": null,
    "IsService": false,
    "AppType": 0,
    "Domain": null,
    "IsChanged": 0,
    "CRank": 0,
    "IsMark": false
  },
  {
    "Id": 0,
    "Rank": 169,
    "TimeRank": 0,
    "DmRank": 0,
    "UseNum": 2112,
    "DayUseNum": null,
    "TimeId": 202406,
    "TimeName": "2024年06月",
    "Appid": 2004,
    "AppName": "凤凰新闻",
    "AppLogo": "//core.itracker.cn/mbapp/logo/2004.png",
    "MachineODayNum": null,
    "MachineODayTime": null,
    "MachineOTimeTime": null,
    "Fclassid": 0,
    "Kclassid": 0,
    "FclassName": "综合资讯",
    "KclassName": "新闻资讯",
    "TimeType": 0,
    "Growth": -2.24,
    "DmGrowth": null,
    "Company": null,
    "UseTime": null,
    "TimeGrowth": null,
    "DayMachineNum": null,
    "IsService": false,
    "AppType": 0,
    "Domain": null,
    "IsChanged": 0,
    "CRank": 0,
    "IsMark": false
  },
  {
    "Id": 0,
    "Rank": 181,
    "TimeRank": 0,
    "DmRank": 0,
    "UseNum": 1939,
    "DayUseNum": null,
    "TimeId": 202406,
    "TimeName": "2024年06月",
    "Appid": 4336,
    "AppName": "新浪财经",
    "AppLogo": "//core.itracker.cn/mbapp/logo/4336.png",
    "MachineODayNum": null,
    "MachineODayTime": null,
    "MachineOTimeTime": null,
    "Fclassid": 0,
    "Kclassid": 0,
    "FclassName": "综合资讯",
    "KclassName": "财经资讯",
    "TimeType": 0,
    "Growth": -0.79,
    "DmGrowth": null,
    "Company": null,
    "UseTime": null,
    "TimeGrowth": null,
    "DayMachineNum": null,
    "IsService": false,
    "AppType": 0,
    "Domain": null,
    "IsChanged": 0,
    "CRank": 0,
    "IsMark": false
  },
  {
    "Id": 0,
    "Rank": 264,
    "TimeRank": 0,
    "DmRank": 0,
    "UseNum": 979,
    "DayUseNum": null,
    "TimeId": 202406,
    "TimeName": "2024年06月",
    "Appid": 7421,
    "AppName": "腾讯体育",
    "AppLogo": "//core.itracker.cn/mbapp/logo/7421.png",
    "MachineODayNum": null,
    "MachineODayTime": null,
    "MachineOTimeTime": null,
    "Fclassid": 0,
    "Kclassid": 0,
    "FclassName": "综合资讯",
    "KclassName": "体育资讯",
    "TimeType": 0,
    "Growth": -6.64,
    "DmGrowth": null,
    "Company": null,
    "UseTime": null,
    "TimeGrowth": null,
    "DayMachineNum": null,
    "IsService": false,
    "AppType": 0,
    "Domain": null,
    "IsChanged": 0,
    "CRank": 0,
    "IsMark": false
  },
  {
    "Id": 0,
    "Rank": 313,
    "TimeRank": 0,
    "DmRank": 0,
    "UseNum": 741,
    "DayUseNum": null,
    "TimeId": 202406,
    "TimeName": "2024年06月",
    "Appid": 15371,
    "AppName": "虎扑",
    "AppLogo": "//core.itracker.cn/mbapp/logo/15371.png",
    "MachineODayNum": null,
    "MachineODayTime": null,
    "MachineOTimeTime": null,
    "Fclassid": 0,
    "Kclassid": 0,
    "FclassName": "综合资讯",
    "KclassName": "体育资讯",
    "TimeType": 0,
    "Growth": -6.76,
    "DmGrowth": null,
    "Company": null,
    "UseTime": null,
    "TimeGrowth": null,
    "DayMachineNum": null,
    "IsService": false,
    "AppType": 0,
    "Domain": null,
    "IsChanged": 0,
    "CRank": 0,
    "IsMark": false
  },
  {
    "Id": 0,
    "Rank": 374,
    "TimeRank": 0,
    "DmRank": 0,
    "UseNum": 534,
    "DayUseNum": null,
    "TimeId": 202406,
    "TimeName": "2024年06月",
    "Appid": 4835,
    "AppName": "直播吧",
    "AppLogo": "//core.itracker.cn/mbapp/logo/4835.png",
    "MachineODayNum": null,
    "MachineODayTime": null,
    "MachineOTimeTime": null,
    "Fclassid": 0,
    "Kclassid": 0,
    "FclassName": "综合资讯",
    "KclassName": "体育资讯",
    "TimeType": 0,
    "Growth": -1.8,
    "DmGrowth": null,
    "Company": null,
    "UseTime": null,
    "TimeGrowth": null,
    "DayMachineNum": null,
    "IsService": false,
    "AppType": 0,
    "Domain": null,
    "IsChanged": 0,
    "CRank": 0,
    "IsMark": false
  },
  {
    "Id": 0,
    "Rank": 466,
    "TimeRank": 0,
    "DmRank": 0,
    "UseNum": 368,
    "DayUseNum": null,
    "TimeId": 202406,
    "TimeName": "2024年06月",
    "Appid": 7443,
    "AppName": "雪球",
    "AppLogo": "//core.itracker.cn/mbapp/logo/7443.png",
    "MachineODayNum": null,
    "MachineODayTime": null,
    "MachineOTimeTime": null,
    "Fclassid": 0,
    "Kclassid": 0,
    "FclassName": "综合资讯",
    "KclassName": "财经资讯",
    "TimeType": 0,
    "Growth": -3.43,
    "DmGrowth": null,
    "Company": null,
    "UseTime": null,
    "TimeGrowth": null,
    "DayMachineNum": null,
    "IsService": false,
    "AppType": 0,
    "Domain": null,
    "IsChanged": 0,
    "CRank": 0,
    "IsMark": false
  },
  {
    "Id": 0,
    "Rank": 548,
    "TimeRank": 0,
    "DmRank": 0,
    "UseNum": 282,
    "DayUseNum": null,
    "TimeId": 202406,
    "TimeName": "2024年06月",
    "Appid": 14984,
    "AppName": "第一财经",
    "AppLogo": "//core.itracker.cn/mbapp/logo/14984.png",
    "MachineODayNum": null,
    "MachineODayTime": null,
    "MachineOTimeTime": null,
    "Fclassid": 0,
    "Kclassid": 0,
    "FclassName": "综合资讯",
    "KclassName": "财经资讯",
    "TimeType": 0,
    "Growth": -3.01,
    "DmGrowth": null,
    "Company": null,
    "UseTime": null,
    "TimeGrowth": null,
    "DayMachineNum": null,
    "IsService": false,
    "AppType": 0,
    "Domain": null,
    "IsChanged": 0,
    "CRank": 0,
    "IsMark": false
  },
  {
    "Id": 0,
    "Rank": 567,
    "TimeRank": 0,
    "DmRank": 0,
    "UseNum": 262,
    "DayUseNum": null,
    "TimeId": 202406,
    "TimeName": "2024年06月",
    "Appid": 15579,
    "AppName": "财联社",
    "AppLogo": "//core.itracker.cn/mbapp/logo/15579.png",
    "MachineODayNum": null,
    "MachineODayTime": null,
    "MachineOTimeTime": null,
    "Fclassid": 0,
    "Kclassid": 0,
    "FclassName": "综合资讯",
    "KclassName": "财经资讯",
    "TimeType": 0,
    "Growth": -1.66,
    "DmGrowth": null,
    "Company": null,
    "UseTime": null,
    "TimeGrowth": null,
    "DayMachineNum": null,
    "IsService": false,
    "AppType": 0,
    "Domain": null,
    "IsChanged": 0,
    "CRank": 0,
    "IsMark": false
  },
  {
    "Id": 0,
    "Rank": 570,
    "TimeRank": 0,
    "DmRank": 0,
    "UseNum": 260,
    "DayUseNum": null,
    "TimeId": 202406,
    "TimeName": "2024年06月",
    "Appid": 10445,
    "AppName": "懂球帝",
    "AppLogo": "//core.itracker.cn/mbapp/logo/10445.png",
    "MachineODayNum": null,
    "MachineODayTime": null,
    "MachineOTimeTime": null,
    "Fclassid": 0,
    "Kclassid": 0,
    "FclassName": "综合资讯",
    "KclassName": "体育资讯",
    "TimeType": 0,
    "Growth": 7.61,
    "DmGrowth": null,
    "Company": null,
    "UseTime": null,
    "TimeGrowth": null,
    "DayMachineNum": null,
    "IsService": false,
    "AppType": 0,
    "Domain": null,
    "IsChanged": 0,
    "CRank": 0,
    "IsMark": false
  },
  {
    "Id": 0,
    "Rank": 575,
    "TimeRank": 0,
    "DmRank": 0,
    "UseNum": 256,
    "DayUseNum": null,
    "TimeId": 202406,
    "TimeName": "2024年06月",
    "Appid": 17877,
    "AppName": "趣头条",
    "AppLogo": "//core.itracker.cn/mbapp/logo/17877.png",
    "MachineODayNum": null,
    "MachineODayTime": null,
    "MachineOTimeTime": null,
    "Fclassid": 0,
    "Kclassid": 0,
    "FclassName": "综合资讯",
    "KclassName": "新闻资讯",
    "TimeType": 0,
    "Growth": -7.9,
    "DmGrowth": null,
    "Company": null,
    "UseTime": null,
    "TimeGrowth": null,
    "DayMachineNum": null,
    "IsService": false,
    "AppType": 0,
    "Domain": null,
    "IsChanged": 0,
    "CRank": 0,
    "IsMark": false
  },
  {
    "Id": 0,
    "Rank": 622,
    "TimeRank": 0,
    "DmRank": 0,
    "UseNum": 229,
    "DayUseNum": null,
    "TimeId": 202406,
    "TimeName": "2024年06月",
    "Appid": 21076,
    "AppName": "南方Plus",
    "AppLogo": "//core.itracker.cn/mbapp/logo/21076.png",
    "MachineODayNum": null,
    "MachineODayTime": null,
    "MachineOTimeTime": null,
    "Fclassid": 0,
    "Kclassid": 0,
    "FclassName": "综合资讯",
    "KclassName": "原创新闻",
    "TimeType": 0,
    "Growth": -3.11,
    "DmGrowth": null,
    "Company": null,
    "UseTime": null,
    "TimeGrowth": null,
    "DayMachineNum": null,
    "IsService": false,
    "AppType": 0,
    "Domain": null,
    "IsChanged": 0,
    "CRank": 0,
    "IsMark": false
  },
  {
    "Id": 0,
    "Rank": 660,
    "TimeRank": 0,
    "DmRank": 0,
    "UseNum": 204,
    "DayUseNum": null,
    "TimeId": 202406,
    "TimeName": "2024年06月",
    "Appid": 12986,
    "AppName": "澎湃新闻",
    "AppLogo": "//core.itracker.cn/mbapp/logo/12986.png",
    "MachineODayNum": null,
    "MachineODayTime": null,
    "MachineOTimeTime": null,
    "Fclassid": 0,
    "Kclassid": 0,
    "FclassName": "综合资讯",
    "KclassName": "原创新闻",
    "TimeType": 0,
    "Growth": -0.26,
    "DmGrowth": null,
    "Company": null,
    "UseTime": null,
    "TimeGrowth": null,
    "DayMachineNum": null,
    "IsService": false,
    "AppType": 0,
    "Domain": null,
    "IsChanged": 0,
    "CRank": 0,
    "IsMark": false
  },
  {
    "Id": 0,
    "Rank": 700,
    "TimeRank": 0,
    "DmRank": 0,
    "UseNum": 188,
    "DayUseNum": null,
    "TimeId": 202406,
    "TimeName": "2024年06月",
    "Appid": 5340,
    "AppName": "央视新闻",
    "AppLogo": "//core.itracker.cn/mbapp/logo/5340.png",
    "MachineODayNum": null,
    "MachineODayTime": null,
    "MachineOTimeTime": null,
    "Fclassid": 0,
    "Kclassid": 0,
    "FclassName": "综合资讯",
    "KclassName": "原创新闻",
    "TimeType": 0,
    "Growth": -1.04,
    "DmGrowth": null,
    "Company": null,
    "UseTime": null,
    "TimeGrowth": null,
    "DayMachineNum": null,
    "IsService": false,
    "AppType": 0,
    "Domain": null,
    "IsChanged": 0,
    "CRank": 0,
    "IsMark": false
  },
  {
    "Id": 0,
    "Rank": 751,
    "TimeRank": 0,
    "DmRank": 0,
    "UseNum": 166,
    "DayUseNum": null,
    "TimeId": 202406,
    "TimeName": "2024年06月",
    "Appid": 3394,
    "AppName": "人民日报",
    "AppLogo": "//core.itracker.cn/mbapp/logo/3394.png",
    "MachineODayNum": null,
    "MachineODayTime": null,
    "MachineOTimeTime": null,
    "Fclassid": 0,
    "Kclassid": 0,
    "FclassName": "综合资讯",
    "KclassName": "原创新闻",
    "TimeType": 0,
    "Growth": -8.01,
    "DmGrowth": null,
    "Company": null,
    "UseTime": null,
    "TimeGrowth": null,
    "DayMachineNum": null,
    "IsService": false,
    "AppType": 0,
    "Domain": null,
    "IsChanged": 0,
    "CRank": 0,
    "IsMark": false
  },
  {
    "Id": 0,
    "Rank": 786,
    "TimeRank": 0,
    "DmRank": 0,
    "UseNum": 157,
    "DayUseNum": null,
    "TimeId": 202406,
    "TimeName": "2024年06月",
    "Appid": 22224,
    "AppName": "雷速体育",
    "AppLogo": "//core.itracker.cn/mbapp/logo/22224.png",
    "MachineODayNum": null,
    "MachineODayTime": null,
    "MachineOTimeTime": null,
    "Fclassid": 0,
    "Kclassid": 0,
    "FclassName": "综合资讯",
    "KclassName": "体育资讯",
    "TimeType": 0,
    "Growth": 6.02,
    "DmGrowth": null,
    "Company": null,
    "UseTime": null,
    "TimeGrowth": null,
    "DayMachineNum": null,
    "IsService": false,
    "AppType": 0,
    "Domain": null,
    "IsChanged": 0,
    "CRank": 0,
    "IsMark": false
  },
  {
    "Id": 0,
    "Rank": 848,
    "TimeRank": 0,
    "DmRank": 0,
    "UseNum": 142,
    "DayUseNum": null,
    "TimeId": 202406,
    "TimeName": "2024年06月",
    "Appid": 78259,
    "AppName": "极光新闻",
    "AppLogo": "//core.itracker.cn/mbapp/logo/78259.png",
    "MachineODayNum": null,
    "MachineODayTime": null,
    "MachineOTimeTime": null,
    "Fclassid": 0,
    "Kclassid": 0,
    "FclassName": "综合资讯",
    "KclassName": "原创新闻",
    "TimeType": 0,
    "Growth": -4.97,
    "DmGrowth": null,
    "Company": null,
    "UseTime": null,
    "TimeGrowth": null,
    "DayMachineNum": null,
    "IsService": false,
    "AppType": 0,
    "Domain": null,
    "IsChanged": 0,
    "CRank": 0,
    "IsMark": false
  },
  {
    "Id": 0,
    "Rank": 883,
    "TimeRank": 0,
    "DmRank": 0,
    "UseNum": 133,
    "DayUseNum": null,
    "TimeId": 202406,
    "TimeName": "2024年06月",
    "Appid": 17827,
    "AppName": "PP体育",
    "AppLogo": "//core.itracker.cn/mbapp/logo/17827.png",
    "MachineODayNum": null,
    "MachineODayTime": null,
    "MachineOTimeTime": null,
    "Fclassid": 0,
    "Kclassid": 0,
    "FclassName": "综合资讯",
    "KclassName": "体育资讯",
    "TimeType": 0,
    "Growth": -3.08,
    "DmGrowth": null,
    "Company": null,
    "UseTime": null,
    "TimeGrowth": null,
    "DayMachineNum": null,
    "IsService": false,
    "AppType": 0,
    "Domain": null,
    "IsChanged": 0,
    "CRank": 0,
    "IsMark": false
  },
  {
    "Id": 0,
    "Rank": 1014,
    "TimeRank": 0,
    "DmRank": 0,
    "UseNum": 109,
    "DayUseNum": null,
    "TimeId": 202406,
    "TimeName": "2024年06月",
    "Appid": 15950,
    "AppName": "界面",
    "AppLogo": "//core.itracker.cn/mbapp/logo/15950.png",
    "MachineODayNum": null,
    "MachineODayTime": null,
    "MachineOTimeTime": null,
    "Fclassid": 0,
    "Kclassid": 0,
    "FclassName": "综合资讯",
    "KclassName": "商业资讯",
    "TimeType": 0,
    "Growth": -4.85,
    "DmGrowth": null,
    "Company": null,
    "UseTime": null,
    "TimeGrowth": null,
    "DayMachineNum": null,
    "IsService": false,
    "AppType": 0,
    "Domain": null,
    "IsChanged": 0,
    "CRank": 0,
    "IsMark": false
  },
  {
    "Id": 0,
    "Rank": 1075,
    "TimeRank": 0,
    "DmRank": 0,
    "UseNum": 101,
    "DayUseNum": null,
    "TimeId": 202406,
    "TimeName": "2024年06月",
    "Appid": 22597,
    "AppName": "中青看点",
    "AppLogo": "//core.itracker.cn/mbapp/logo/22597.png",
    "MachineODayNum": null,
    "MachineODayTime": null,
    "MachineOTimeTime": null,
    "Fclassid": 0,
    "Kclassid": 0,
    "FclassName": "综合资讯",
    "KclassName": "原创新闻",
    "TimeType": 0,
    "Growth": -1.01,
    "DmGrowth": null,
    "Company": null,
    "UseTime": null,
    "TimeGrowth": null,
    "DayMachineNum": null,
    "IsService": false,
    "AppType": 0,
    "Domain": null,
    "IsChanged": 0,
    "CRank": 0,
    "IsMark": false
  },
  {
    "Id": 0,
    "Rank": 1153,
    "TimeRank": 0,
    "DmRank": 0,
    "UseNum": 92,
    "DayUseNum": null,
    "TimeId": 202406,
    "TimeName": "2024年06月",
    "Appid": 192368,
    "AppName": "广西扶贫",
    "AppLogo": "//core.itracker.cn/mbapp/logo/192368.png",
    "MachineODayNum": null,
    "MachineODayTime": null,
    "MachineOTimeTime": null,
    "Fclassid": 0,
    "Kclassid": 0,
    "FclassName": "综合资讯",
    "KclassName": "其他",
    "TimeType": 0,
    "Growth": -4.5,
    "DmGrowth": null,
    "Company": null,
    "UseTime": null,
    "TimeGrowth": null,
    "DayMachineNum": null,
    "IsService": false,
    "AppType": 0,
    "Domain": null,
    "IsChanged": 0,
    "CRank": 0,
    "IsMark": false
  },
  {
    "Id": 0,
    "Rank": 1236,
    "TimeRank": 0,
    "DmRank": 0,
    "UseNum": 85,
    "DayUseNum": null,
    "TimeId": 202406,
    "TimeName": "2024年06月",
    "Appid": 15712,
    "AppName": "海报新闻",
    "AppLogo": "//core.itracker.cn/mbapp/logo/15712.png",
    "MachineODayNum": null,
    "MachineODayTime": null,
    "MachineOTimeTime": null,
    "Fclassid": 0,
    "Kclassid": 0,
    "FclassName": "综合资讯",
    "KclassName": "原创新闻",
    "TimeType": 0,
    "Growth": -3.99,
    "DmGrowth": null,
    "Company": null,
    "UseTime": null,
    "TimeGrowth": null,
    "DayMachineNum": null,
    "IsService": false,
    "AppType": 0,
    "Domain": null,
    "IsChanged": 0,
    "CRank": 0,
    "IsMark": false
  },
  {
    "Id": 0,
    "Rank": 1249,
    "TimeRank": 0,
    "DmRank": 0,
    "UseNum": 83,
    "DayUseNum": null,
    "TimeId": 202406,
    "TimeName": "2024年06月",
    "Appid": 4714,
    "AppName": "ZAKER新闻",
    "AppLogo": "//core.itracker.cn/mbapp/logo/4714.png",
    "MachineODayNum": null,
    "MachineODayTime": null,
    "MachineOTimeTime": null,
    "Fclassid": 0,
    "Kclassid": 0,
    "FclassName": "综合资讯",
    "KclassName": "新闻资讯",
    "TimeType": 0,
    "Growth": -5.15,
    "DmGrowth": null,
    "Company": null,
    "UseTime": null,
    "TimeGrowth": null,
    "DayMachineNum": null,
    "IsService": false,
    "AppType": 0,
    "Domain": null,
    "IsChanged": 0,
    "CRank": 0,
    "IsMark": false
  },
  {
    "Id": 0,
    "Rank": 1282,
    "TimeRank": 0,
    "DmRank": 0,
    "UseNum": 81,
    "DayUseNum": null,
    "TimeId": 202406,
    "TimeName": "2024年06月",
    "Appid": 182796,
    "AppName": "中国体育",
    "AppLogo": "//core.itracker.cn/mbapp/logo/182796.png",
    "MachineODayNum": null,
    "MachineODayTime": null,
    "MachineOTimeTime": null,
    "Fclassid": 0,
    "Kclassid": 0,
    "FclassName": "综合资讯",
    "KclassName": "体育资讯",
    "TimeType": 0,
    "Growth": -3.89,
    "DmGrowth": null,
    "Company": null,
    "UseTime": null,
    "TimeGrowth": null,
    "DayMachineNum": null,
    "IsService": false,
    "AppType": 0,
    "Domain": null,
    "IsChanged": 0,
    "CRank": 0,
    "IsMark": false
  },
  {
    "Id": 0,
    "Rank": 1401,
    "TimeRank": 0,
    "DmRank": 0,
    "UseNum": 72,
    "DayUseNum": null,
    "TimeId": 202406,
    "TimeName": "2024年06月",
    "Appid": 1463,
    "AppName": "财新网",
    "AppLogo": "//core.itracker.cn/mbapp/logo/1463.png",
    "MachineODayNum": null,
    "MachineODayTime": null,
    "MachineOTimeTime": null,
    "Fclassid": 0,
    "Kclassid": 0,
    "FclassName": "综合资讯",
    "KclassName": "商业资讯",
    "TimeType": 0,
    "Growth": -1.28,
    "DmGrowth": null,
    "Company": null,
    "UseTime": null,
    "TimeGrowth": null,
    "DayMachineNum": null,
    "IsService": false,
    "AppType": 0,
    "Domain": null,
    "IsChanged": 0,
    "CRank": 0,
    "IsMark": false
  }
]