[
  {
    "Id": 0,
    "Rank": 11,
    "TimeRank": 0,
    "DmRank": 0,
    "UseNum": 53158,
    "DayUseNum": null,
    "TimeId": 202605,
    "TimeName": "2026年05月",
    "Appid": 3278,
    "AppName": "爱奇艺",
    "AppLogo": "//core.itracker.cn/mbapp/logo/3278.png",
    "MachineODayNum": null,
    "MachineODayTime": null,
    "MachineOTimeTime": null,
    "Fclassid": 0,
    "Kclassid": 0,
    "FclassName": "视频服务",
    "KclassName": "在线视频",
    "TimeType": 0,
    "Growth": 1.67,
    "DmGrowth": null,
    "Company": null,
    "UseTime": null,
    "TimeGrowth": null,
    "DayMachineNum": null,
    "IsService": false,
    "AppType": 0,
    "Domain": null,
    "IsChanged": 0,
    "CRank": 0,
    "IsMark": false
  },
  {
    "Id": 0,
    "Rank": 18,
    "TimeRank": 0,
    "DmRank": 0,
    "UseNum": 42007,
    "DayUseNum": null,
    "TimeId": 202605,
    "TimeName": "2026年05月",
    "Appid": 3856,
    "AppName": "腾讯视频",
    "AppLogo": "//core.itracker.cn/mbapp/logo/3856.png",
    "MachineODayNum": null,
    "MachineODayTime": null,
    "MachineOTimeTime": null,
    "Fclassid": 0,
    "Kclassid": 0,
    "FclassName": "视频服务",
    "KclassName": "在线视频",
    "TimeType": 0,
    "Growth": -0.23,
    "DmGrowth": null,
    "Company": null,
    "UseTime": null,
    "TimeGrowth": null,
    "DayMachineNum": null,
    "IsService": false,
    "AppType": 0,
    "Domain": null,
    "IsChanged": 0,
    "CRank": 0,
    "IsMark": false
  },
  {
    "Id": 0,
    "Rank": 26,
    "TimeRank": 0,
    "DmRank": 0,
    "UseNum": 28945,
    "DayUseNum": null,
    "TimeId": 202605,
    "TimeName": "2026年05月",
    "Appid": 4606,
    "AppName": "优酷视频",
    "AppLogo": "//core.itracker.cn/mbapp/logo/4606.png",
    "MachineODayNum": null,
    "MachineODayTime": null,
    "MachineOTimeTime": null,
    "Fclassid": 0,
    "Kclassid": 0,
    "FclassName": "视频服务",
    "KclassName": "在线视频",
    "TimeType": 0,
    "Growth": -0.05,
    "DmGrowth": null,
    "Company": null,
    "UseTime": null,
    "TimeGrowth": null,
    "DayMachineNum": null,
    "IsService": false,
    "AppType": 0,
    "Domain": null,
    "IsChanged": 0,
    "CRank": 0,
    "IsMark": false
  },
  {
    "Id": 0,
    "Rank": 28,
    "TimeRank": 0,
    "DmRank": 0,
    "UseNum": 26296,
    "DayUseNum": null,
    "TimeId": 202605,
    "TimeName": "2026年05月",
    "Appid": 2956,
    "AppName": "芒果TV",
    "AppLogo": "//core.itracker.cn/mbapp/logo/2956.png",
    "MachineODayNum": null,
    "MachineODayTime": null,
    "MachineOTimeTime": null,
    "Fclassid": 0,
    "Kclassid": 0,
    "FclassName": "视频服务",
    "KclassName": "在线视频",
    "TimeType": 0,
    "Growth": 1.82,
    "DmGrowth": null,
    "Company": null,
    "UseTime": null,
    "TimeGrowth": null,
    "DayMachineNum": null,
    "IsService": false,
    "AppType": 0,
    "Domain": null,
    "IsChanged": 0,
    "CRank": 0,
    "IsMark": false
  },
  {
    "Id": 0,
    "Rank": 36,
    "TimeRank": 0,
    "DmRank": 0,
    "UseNum": 22058,
    "DayUseNum": null,
    "TimeId": 202605,
    "TimeName": "2026年05月",
    "Appid": 1398,
    "AppName": "哔哩哔哩",
    "AppLogo": "//core.itracker.cn/mbapp/logo/1398.png",
    "MachineODayNum": null,
    "MachineODayTime": null,
    "MachineOTimeTime": null,
    "Fclassid": 0,
    "Kclassid": 0,
    "FclassName": "视频服务",
    "KclassName": "聚合视频",
    "TimeType": 0,
    "Growth": 2.25,
    "DmGrowth": null,
    "Company": null,
    "UseTime": null,
    "TimeGrowth": null,
    "DayMachineNum": null,
    "IsService": false,
    "AppType": 0,
    "Domain": null,
    "IsChanged": 0,
    "CRank": 0,
    "IsMark": false
  },
  {
    "Id": 0,
    "Rank": 53,
    "TimeRank": 0,
    "DmRank": 0,
    "UseNum": 15493,
    "DayUseNum": null,
    "TimeId": 202605,
    "TimeName": "2026年05月",
    "Appid": 4917,
    "AppName": "咪咕视频",
    "AppLogo": "//core.itracker.cn/mbapp/logo/4917.png",
    "MachineODayNum": null,
    "MachineODayTime": null,
    "MachineOTimeTime": null,
    "Fclassid": 0,
    "Kclassid": 0,
    "FclassName": "视频服务",
    "KclassName": "聚合视频",
    "TimeType": 0,
    "Growth": 0.71,
    "DmGrowth": null,
    "Company": null,
    "UseTime": null,
    "TimeGrowth": null,
    "DayMachineNum": null,
    "IsService": false,
    "AppType": 0,
    "Domain": null,
    "IsChanged": 0,
    "CRank": 0,
    "IsMark": false
  },
  {
    "Id": 0,
    "Rank": 64,
    "TimeRank": 0,
    "DmRank": 0,
    "UseNum": 13910,
    "DayUseNum": null,
    "TimeId": 202605,
    "TimeName": "2026年05月",
    "Appid": 16134,
    "AppName": "小米视频",
    "AppLogo": "//core.itracker.cn/mbapp/logo/16134.png",
    "MachineODayNum": null,
    "MachineODayTime": null,
    "MachineOTimeTime": null,
    "Fclassid": 0,
    "Kclassid": 0,
    "FclassName": "视频服务",
    "KclassName": "聚合视频",
    "TimeType": 0,
    "Growth": 7.45,
    "DmGrowth": null,
    "Company": null,
    "UseTime": null,
    "TimeGrowth": null,
    "DayMachineNum": null,
    "IsService": false,
    "AppType": 0,
    "Domain": null,
    "IsChanged": 0,
    "CRank": 0,
    "IsMark": false
  },
  {
    "Id": 0,
    "Rank": 108,
    "TimeRank": 0,
    "DmRank": 0,
    "UseNum": 6463,
    "DayUseNum": null,
    "TimeId": 202605,
    "TimeName": "2026年05月",
    "Appid": 3142,
    "AppName": "MOMO陌陌",
    "AppLogo": "//core.itracker.cn/mbapp/logo/3142.png",
    "MachineODayNum": null,
    "MachineODayTime": null,
    "MachineOTimeTime": null,
    "Fclassid": 0,
    "Kclassid": 0,
    "FclassName": "视频服务",
    "KclassName": "社交直播",
    "TimeType": 0,
    "Growth": 1.35,
    "DmGrowth": null,
    "Company": null,
    "UseTime": null,
    "TimeGrowth": null,
    "DayMachineNum": null,
    "IsService": false,
    "AppType": 0,
    "Domain": null,
    "IsChanged": 0,
    "CRank": 0,
    "IsMark": false
  },
  {
    "Id": 0,
    "Rank": 113,
    "TimeRank": 0,
    "DmRank": 0,
    "UseNum": 5885,
    "DayUseNum": null,
    "TimeId": 202605,
    "TimeName": "2026年05月",
    "Appid": 17599,
    "AppName": "华为视频",
    "AppLogo": "//core.itracker.cn/mbapp/logo/17599.png",
    "MachineODayNum": null,
    "MachineODayTime": null,
    "MachineOTimeTime": null,
    "Fclassid": 0,
    "Kclassid": 0,
    "FclassName": "视频服务",
    "KclassName": "聚合视频",
    "TimeType": 0,
    "Growth": -0.93,
    "DmGrowth": null,
    "Company": null,
    "UseTime": null,
    "TimeGrowth": null,
    "DayMachineNum": null,
    "IsService": false,
    "AppType": 0,
    "Domain": null,
    "IsChanged": 0,
    "CRank": 0,
    "IsMark": false
  },
  {
    "Id": 0,
    "Rank": 114,
    "TimeRank": 0,
    "DmRank": 0,
    "UseNum": 5879,
    "DayUseNum": null,
    "TimeId": 202605,
    "TimeName": "2026年05月",
    "Appid": 190685,
    "AppName": "剪映",
    "AppLogo": "//core.itracker.cn/mbapp/logo/190685.png",
    "MachineODayNum": null,
    "MachineODayTime": null,
    "MachineOTimeTime": null,
    "Fclassid": 0,
    "Kclassid": 0,
    "FclassName": "视频服务",
    "KclassName": "视频工具",
    "TimeType": 0,
    "Growth": -0.42,
    "DmGrowth": null,
    "Company": null,
    "UseTime": null,
    "TimeGrowth": null,
    "DayMachineNum": null,
    "IsService": false,
    "AppType": 0,
    "Domain": null,
    "IsChanged": 0,
    "CRank": 0,
    "IsMark": false
  },
  {
    "Id": 0,
    "Rank": 128,
    "TimeRank": 0,
    "DmRank": 0,
    "UseNum": 5058,
    "DayUseNum": null,
    "TimeId": 202605,
    "TimeName": "2026年05月",
    "Appid": 3755,
    "AppName": "搜狐视频",
    "AppLogo": "//core.itracker.cn/mbapp/logo/3755.png",
    "MachineODayNum": null,
    "MachineODayTime": null,
    "MachineOTimeTime": null,
    "Fclassid": 0,
    "Kclassid": 0,
    "FclassName": "视频服务",
    "KclassName": "在线视频",
    "TimeType": 0,
    "Growth": 0.74,
    "DmGrowth": null,
    "Company": null,
    "UseTime": null,
    "TimeGrowth": null,
    "DayMachineNum": null,
    "IsService": false,
    "AppType": 0,
    "Domain": null,
    "IsChanged": 0,
    "CRank": 0,
    "IsMark": false
  },
  {
    "Id": 0,
    "Rank": 164,
    "TimeRank": 0,
    "DmRank": 0,
    "UseNum": 3083,
    "DayUseNum": null,
    "TimeId": 202605,
    "TimeName": "2026年05月",
    "Appid": 192358,
    "AppName": "央视频",
    "AppLogo": "//core.itracker.cn/mbapp/logo/192358.png",
    "MachineODayNum": null,
    "MachineODayTime": null,
    "MachineOTimeTime": null,
    "Fclassid": 0,
    "Kclassid": 0,
    "FclassName": "视频服务",
    "KclassName": "资讯视频",
    "TimeType": 0,
    "Growth": 31.16,
    "DmGrowth": null,
    "Company": null,
    "UseTime": null,
    "TimeGrowth": null,
    "DayMachineNum": null,
    "IsService": false,
    "AppType": 0,
    "Domain": null,
    "IsChanged": 0,
    "CRank": 0,
    "IsMark": false
  },
  {
    "Id": 0,
    "Rank": 167,
    "TimeRank": 0,
    "DmRank": 0,
    "UseNum": 2969,
    "DayUseNum": null,
    "TimeId": 202605,
    "TimeName": "2026年05月",
    "Appid": 10455,
    "AppName": "斗鱼",
    "AppLogo": "//core.itracker.cn/mbapp/logo/10455.png",
    "MachineODayNum": null,
    "MachineODayTime": null,
    "MachineOTimeTime": null,
    "Fclassid": 0,
    "Kclassid": 0,
    "FclassName": "视频服务",
    "KclassName": "游戏直播",
    "TimeType": 0,
    "Growth": -2.01,
    "DmGrowth": null,
    "Company": null,
    "UseTime": null,
    "TimeGrowth": null,
    "DayMachineNum": null,
    "IsService": false,
    "AppType": 0,
    "Domain": null,
    "IsChanged": 0,
    "CRank": 0,
    "IsMark": false
  },
  {
    "Id": 0,
    "Rank": 179,
    "TimeRank": 0,
    "DmRank": 0,
    "UseNum": 2521,
    "DayUseNum": null,
    "TimeId": 202605,
    "TimeName": "2026年05月",
    "Appid": 1962,
    "AppName": "风行视频",
    "AppLogo": "//core.itracker.cn/mbapp/logo/1962.png",
    "MachineODayNum": null,
    "MachineODayTime": null,
    "MachineOTimeTime": null,
    "Fclassid": 0,
    "Kclassid": 0,
    "FclassName": "视频服务",
    "KclassName": "在线视频",
    "TimeType": 0,
    "Growth": -0.87,
    "DmGrowth": null,
    "Company": null,
    "UseTime": null,
    "TimeGrowth": null,
    "DayMachineNum": null,
    "IsService": false,
    "AppType": 0,
    "Domain": null,
    "IsChanged": 0,
    "CRank": 0,
    "IsMark": false
  },
  {
    "Id": 0,
    "Rank": 195,
    "TimeRank": 0,
    "DmRank": 0,
    "UseNum": 2107,
    "DayUseNum": null,
    "TimeId": 202605,
    "TimeName": "2026年05月",
    "Appid": 12183,
    "AppName": "虎牙直播",
    "AppLogo": "//core.itracker.cn/mbapp/logo/12183.png",
    "MachineODayNum": null,
    "MachineODayTime": null,
    "MachineOTimeTime": null,
    "Fclassid": 0,
    "Kclassid": 0,
    "FclassName": "视频服务",
    "KclassName": "游戏直播",
    "TimeType": 0,
    "Growth": -1.49,
    "DmGrowth": null,
    "Company": null,
    "UseTime": null,
    "TimeGrowth": null,
    "DayMachineNum": null,
    "IsService": false,
    "AppType": 0,
    "Domain": null,
    "IsChanged": 0,
    "CRank": 0,
    "IsMark": false
  },
  {
    "Id": 0,
    "Rank": 198,
    "TimeRank": 0,
    "DmRank": 0,
    "UseNum": 2089,
    "DayUseNum": null,
    "TimeId": 202605,
    "TimeName": "2026年05月",
    "Appid": 39883,
    "AppName": "快影",
    "AppLogo": "//core.itracker.cn/mbapp/logo/39883.png",
    "MachineODayNum": null,
    "MachineODayTime": null,
    "MachineOTimeTime": null,
    "Fclassid": 0,
    "Kclassid": 0,
    "FclassName": "视频服务",
    "KclassName": "视频工具",
    "TimeType": 0,
    "Growth": 2.37,
    "DmGrowth": null,
    "Company": null,
    "UseTime": null,
    "TimeGrowth": null,
    "DayMachineNum": null,
    "IsService": false,
    "AppType": 0,
    "Domain": null,
    "IsChanged": 0,
    "CRank": 0,
    "IsMark": false
  },
  {
    "Id": 0,
    "Rank": 230,
    "TimeRank": 0,
    "DmRank": 0,
    "UseNum": 1486,
    "DayUseNum": null,
    "TimeId": 202605,
    "TimeName": "2026年05月",
    "Appid": 778,
    "AppName": "PP视频",
    "AppLogo": "//core.itracker.cn/mbapp/logo/778.png",
    "MachineODayNum": null,
    "MachineODayTime": null,
    "MachineOTimeTime": null,
    "Fclassid": 0,
    "Kclassid": 0,
    "FclassName": "视频服务",
    "KclassName": "在线视频",
    "TimeType": 0,
    "Growth": -1.16,
    "DmGrowth": null,
    "Company": null,
    "UseTime": null,
    "TimeGrowth": null,
    "DayMachineNum": null,
    "IsService": false,
    "AppType": 0,
    "Domain": null,
    "IsChanged": 0,
    "CRank": 0,
    "IsMark": false
  },
  {
    "Id": 0,
    "Rank": 264,
    "TimeRank": 0,
    "DmRank": 0,
    "UseNum": 1226,
    "DayUseNum": null,
    "TimeId": 202605,
    "TimeName": "2026年05月",
    "Appid": 7684,
    "AppName": "央视影音",
    "AppLogo": "//core.itracker.cn/mbapp/logo/7684.png",
    "MachineODayNum": null,
    "MachineODayTime": null,
    "MachineOTimeTime": null,
    "Fclassid": 0,
    "Kclassid": 0,
    "FclassName": "视频服务",
    "KclassName": "电视直播",
    "TimeType": 0,
    "Growth": 7.02,
    "DmGrowth": null,
    "Company": null,
    "UseTime": null,
    "TimeGrowth": null,
    "DayMachineNum": null,
    "IsService": false,
    "AppType": 0,
    "Domain": null,
    "IsChanged": 0,
    "CRank": 0,
    "IsMark": false
  },
  {
    "Id": 0,
    "Rank": 355,
    "TimeRank": 0,
    "DmRank": 0,
    "UseNum": 677,
    "DayUseNum": null,
    "TimeId": 202605,
    "TimeName": "2026年05月",
    "Appid": 15908,
    "AppName": "Z视介",
    "AppLogo": "//core.itracker.cn/mbapp/logo/15908.png",
    "MachineODayNum": null,
    "MachineODayTime": null,
    "MachineOTimeTime": null,
    "Fclassid": 0,
    "Kclassid": 0,
    "FclassName": "视频服务",
    "KclassName": "在线视频",
    "TimeType": 0,
    "Growth": 18.57,
    "DmGrowth": null,
    "Company": null,
    "UseTime": null,
    "TimeGrowth": null,
    "DayMachineNum": null,
    "IsService": false,
    "AppType": 0,
    "Domain": null,
    "IsChanged": 0,
    "CRank": 0,
    "IsMark": false
  },
  {
    "Id": 0,
    "Rank": 405,
    "TimeRank": 0,
    "DmRank": 0,
    "UseNum": 517,
    "DayUseNum": null,
    "TimeId": 202605,
    "TimeName": "2026年05月",
    "Appid": 15781,
    "AppName": "有看头",
    "AppLogo": "//core.itracker.cn/mbapp/logo/15781.png",
    "MachineODayNum": null,
    "MachineODayTime": null,
    "MachineOTimeTime": null,
    "Fclassid": 0,
    "Kclassid": 0,
    "FclassName": "视频服务",
    "KclassName": "其他",
    "TimeType": 0,
    "Growth": -2.43,
    "DmGrowth": null,
    "Company": null,
    "UseTime": null,
    "TimeGrowth": null,
    "DayMachineNum": null,
    "IsService": false,
    "AppType": 0,
    "Domain": null,
    "IsChanged": 0,
    "CRank": 0,
    "IsMark": false
  },
  {
    "Id": 0,
    "Rank": 418,
    "TimeRank": 0,
    "DmRank": 0,
    "UseNum": 480,
    "DayUseNum": null,
    "TimeId": 202605,
    "TimeName": "2026年05月",
    "Appid": 20309,
    "AppName": "南瓜电影",
    "AppLogo": "//core.itracker.cn/mbapp/logo/20309.png",
    "MachineODayNum": null,
    "MachineODayTime": null,
    "MachineOTimeTime": null,
    "Fclassid": 0,
    "Kclassid": 0,
    "FclassName": "视频服务",
    "KclassName": "视频播放器",
    "TimeType": 0,
    "Growth": 70.46,
    "DmGrowth": null,
    "Company": null,
    "UseTime": null,
    "TimeGrowth": null,
    "DayMachineNum": null,
    "IsService": false,
    "AppType": 0,
    "Domain": null,
    "IsChanged": 0,
    "CRank": 0,
    "IsMark": false
  },
  {
    "Id": 0,
    "Rank": 420,
    "TimeRank": 0,
    "DmRank": 0,
    "UseNum": 478,
    "DayUseNum": null,
    "TimeId": 202605,
    "TimeName": "2026年05月",
    "Appid": 1282,
    "AppName": "百搜视频（原百度视频）",
    "AppLogo": "//core.itracker.cn/mbapp/logo/1282.png",
    "MachineODayNum": null,
    "MachineODayTime": null,
    "MachineOTimeTime": null,
    "Fclassid": 0,
    "Kclassid": 0,
    "FclassName": "视频服务",
    "KclassName": "聚合视频",
    "TimeType": 0,
    "Growth": -12.25,
    "DmGrowth": null,
    "Company": null,
    "UseTime": null,
    "TimeGrowth": null,
    "DayMachineNum": null,
    "IsService": false,
    "AppType": 0,
    "Domain": null,
    "IsChanged": 0,
    "CRank": 0,
    "IsMark": false
  },
  {
    "Id": 0,
    "Rank": 450,
    "TimeRank": 0,
    "DmRank": 0,
    "UseNum": 425,
    "DayUseNum": null,
    "TimeId": 202605,
    "TimeName": "2026年05月",
    "Appid": 1137,
    "AppName": "YY",
    "AppLogo": "//core.itracker.cn/mbapp/logo/1137.png",
    "MachineODayNum": null,
    "MachineODayTime": null,
    "MachineOTimeTime": null,
    "Fclassid": 0,
    "Kclassid": 0,
    "FclassName": "视频服务",
    "KclassName": "社交直播",
    "TimeType": 0,
    "Growth": -7.88,
    "DmGrowth": null,
    "Company": null,
    "UseTime": null,
    "TimeGrowth": null,
    "DayMachineNum": null,
    "IsService": false,
    "AppType": 0,
    "Domain": null,
    "IsChanged": 0,
    "CRank": 0,
    "IsMark": false
  },
  {
    "Id": 0,
    "Rank": 454,
    "TimeRank": 0,
    "DmRank": 0,
    "UseNum": 422,
    "DayUseNum": null,
    "TimeId": 202605,
    "TimeName": "2026年05月",
    "Appid": 15730,
    "AppName": "糖豆",
    "AppLogo": "//core.itracker.cn/mbapp/logo/15730.png",
    "MachineODayNum": null,
    "MachineODayTime": null,
    "MachineOTimeTime": null,
    "Fclassid": 0,
    "Kclassid": 0,
    "FclassName": "视频服务",
    "KclassName": "其他",
    "TimeType": 0,
    "Growth": -2.01,
    "DmGrowth": null,
    "Company": null,
    "UseTime": null,
    "TimeGrowth": null,
    "DayMachineNum": null,
    "IsService": false,
    "AppType": 0,
    "Domain": null,
    "IsChanged": 0,
    "CRank": 0,
    "IsMark": false
  },
  {
    "Id": 0,
    "Rank": 467,
    "TimeRank": 0,
    "DmRank": 0,
    "UseNum": 408,
    "DayUseNum": null,
    "TimeId": 202605,
    "TimeName": "2026年05月",
    "Appid": 1363,
    "AppName": "暴风影音",
    "AppLogo": "//core.itracker.cn/mbapp/logo/1363.png",
    "MachineODayNum": null,
    "MachineODayTime": null,
    "MachineOTimeTime": null,
    "Fclassid": 0,
    "Kclassid": 0,
    "FclassName": "视频服务",
    "KclassName": "聚合视频",
    "TimeType": 0,
    "Growth": 0.55,
    "DmGrowth": null,
    "Company": null,
    "UseTime": null,
    "TimeGrowth": null,
    "DayMachineNum": null,
    "IsService": false,
    "AppType": 0,
    "Domain": null,
    "IsChanged": 0,
    "CRank": 0,
    "IsMark": false
  },
  {
    "Id": 0,
    "Rank": 603,
    "TimeRank": 0,
    "DmRank": 0,
    "UseNum": 265,
    "DayUseNum": null,
    "TimeId": 202605,
    "TimeName": "2026年05月",
    "Appid": 15817,
    "AppName": "花椒直播",
    "AppLogo": "//core.itracker.cn/mbapp/logo/15817.png",
    "MachineODayNum": null,
    "MachineODayTime": null,
    "MachineOTimeTime": null,
    "Fclassid": 0,
    "Kclassid": 0,
    "FclassName": "视频服务",
    "KclassName": "社交直播",
    "TimeType": 0,
    "Growth": -4.76,
    "DmGrowth": null,
    "Company": null,
    "UseTime": null,
    "TimeGrowth": null,
    "DayMachineNum": null,
    "IsService": false,
    "AppType": 0,
    "Domain": null,
    "IsChanged": 0,
    "CRank": 0,
    "IsMark": false
  },
  {
    "Id": 0,
    "Rank": 607,
    "TimeRank": 0,
    "DmRank": 0,
    "UseNum": 263,
    "DayUseNum": null,
    "TimeId": 202605,
    "TimeName": "2026年05月",
    "Appid": 194839,
    "AppName": "睿博士",
    "AppLogo": "//core.itracker.cn/mbapp/logo/194839.png",
    "MachineODayNum": null,
    "MachineODayTime": null,
    "MachineOTimeTime": null,
    "Fclassid": 0,
    "Kclassid": 0,
    "FclassName": "视频服务",
    "KclassName": "视频工具",
    "TimeType": 0,
    "Growth": -1.91,
    "DmGrowth": null,
    "Company": null,
    "UseTime": null,
    "TimeGrowth": null,
    "DayMachineNum": null,
    "IsService": false,
    "AppType": 0,
    "Domain": null,
    "IsChanged": 0,
    "CRank": 0,
    "IsMark": false
  },
  {
    "Id": 0,
    "Rank": 622,
    "TimeRank": 0,
    "DmRank": 0,
    "UseNum": 254,
    "DayUseNum": null,
    "TimeId": 202605,
    "TimeName": "2026年05月",
    "Appid": 10066,
    "AppName": "AcFun",
    "AppLogo": "//core.itracker.cn/mbapp/logo/10066.png",
    "MachineODayNum": null,
    "MachineODayTime": null,
    "MachineOTimeTime": null,
    "Fclassid": 0,
    "Kclassid": 0,
    "FclassName": "视频服务",
    "KclassName": "聚合视频",
    "TimeType": 0,
    "Growth": -22.73,
    "DmGrowth": null,
    "Company": null,
    "UseTime": null,
    "TimeGrowth": null,
    "DayMachineNum": null,
    "IsService": false,
    "AppType": 0,
    "Domain": null,
    "IsChanged": 0,
    "CRank": 0,
    "IsMark": false
  },
  {
    "Id": 0,
    "Rank": 644,
    "TimeRank": 0,
    "DmRank": 0,
    "UseNum": 240,
    "DayUseNum": null,
    "TimeId": 202605,
    "TimeName": "2026年05月",
    "Appid": 17647,
    "AppName": "韩小圈（原韩剧TV）",
    "AppLogo": "//core.itracker.cn/mbapp/logo/17647.png",
    "MachineODayNum": null,
    "MachineODayTime": null,
    "MachineOTimeTime": null,
    "Fclassid": 0,
    "Kclassid": 0,
    "FclassName": "视频服务",
    "KclassName": "聚合视频",
    "TimeType": 0,
    "Growth": 4.05,
    "DmGrowth": null,
    "Company": null,
    "UseTime": null,
    "TimeGrowth": null,
    "DayMachineNum": null,
    "IsService": false,
    "AppType": 0,
    "Domain": null,
    "IsChanged": 0,
    "CRank": 0,
    "IsMark": false
  },
  {
    "Id": 0,
    "Rank": 671,
    "TimeRank": 0,
    "DmRank": 0,
    "UseNum": 220,
    "DayUseNum": null,
    "TimeId": 202605,
    "TimeName": "2026年05月",
    "Appid": 8679,
    "AppName": "央视体育",
    "AppLogo": "//core.itracker.cn/mbapp/logo/8679.png",
    "MachineODayNum": null,
    "MachineODayTime": null,
    "MachineOTimeTime": null,
    "Fclassid": 0,
    "Kclassid": 0,
    "FclassName": "视频服务",
    "KclassName": "电视直播",
    "TimeType": 0,
    "Growth": 50.53,
    "DmGrowth": null,
    "Company": null,
    "UseTime": null,
    "TimeGrowth": null,
    "DayMachineNum": null,
    "IsService": false,
    "AppType": 0,
    "Domain": null,
    "IsChanged": 0,
    "CRank": 0,
    "IsMark": false
  }
]